research/__init__.py
research/app/__init__.py
research/app/main.py
research/app/static/.keepit
research/app/templates/base.html
research/app/templates/dashboard.html
research/app/templates/demographics.html
research/app/templates/diagnosis.html
research/app/templates/done.html
research/app/templates/exams.html
research/app/templates/language.html
research/app/templates/lifestyle.html
research/app/templates/mental.html
research/app/templates/patient.html
research/app/templates/symptoms.html
research/app/templates/tests.html
research/app/templates/wearable.html
research/cli.py
research/models/__init__.py
research/models/repositories.py
sdx/__init__.py
sdx/agents/__init__.py
sdx/agents/client.py
sdx/agents/diagnostics/__init__.py
sdx/agents/diagnostics/core.py
sdx/agents/extraction/__init__.py
sdx/agents/extraction/medical_reports.py
sdx/agents/extraction/wearable.py
sdx/agents/treatments/__init__.py
sdx/models/__init__.py
sdx/models/sqla/__init__.py
sdx/models/sqla/fhir.py
sdx/models/sqlmodel/__init__.py
sdx/models/sqlmodel/fhir.py
sdx/py.typed
sdx/schema/__init__.py
sdx/schema/clinical_outputs.py
sdx/schema/fhir.py
sdx/schema/human_evaluations.py
sdx/sdx.py
sdx/utils.py
sdx-0.2.0.dist-info/LICENSE
sdx-0.2.0.dist-info/METADATA
sdx-0.2.0.dist-info/WHEEL
sdx-0.2.0.dist-info/RECORD
