Metadata-Version: 2.3
Name: sdx
Version: 0.2.0
Summary: This Project aims to ...
License: BSD 3 Clause
Author: Ivan Ogasawara
Author-email: ivan.ogasawara@gmail.com
Requires-Python: >=3.9,<3.13
Classifier: License :: Other/Proprietary License
Classifier: Programming Language :: Python :: 3
Classifier: Programming Language :: Python :: 3.9
Classifier: Programming Language :: Python :: 3.10
Classifier: Programming Language :: Python :: 3.11
Classifier: Programming Language :: Python :: 3.12
Requires-Dist: anamnesisai (>=0.2.1)
Requires-Dist: atpublic (>=6)
Requires-Dist: pillow (>=11.3.0,<12.0.0)
Requires-Dist: pypdf (>=5.4.0)
Requires-Dist: pytesseract (>=0.3.13,<0.4.0)
Requires-Dist: python-magic (>=0.4.27,<0.5.0)
Requires-Dist: questionary (>=2.1.0,<3.0.0)
Requires-Dist: rago (>=0.13.0)
Requires-Dist: sqlalchemy (>=2.0.41,<3.0.0)
Requires-Dist: sqlmodel (>=0.0.24)
